{
  "db_name": "PostgreSQL",
  "query": "\n                SELECT\n                    u.id as user_id, u.username, u.role as \"role:_\",\n                    s.token_hash, s.created_at, s.expires_at\n                FROM user_sessions as s\n                JOIN users as u ON u.id = s.user_id\n                WHERE s.token_hash = $1\n                ",
  "describe": {
    "columns": [
      {
        "ordinal": 0,
        "name": "user_id",
        "type_info": "Int4"
      },
      {
        "ordinal": 1,
        "name": "username",
        "type_info": "Varchar"
      },
      {
        "ordinal": 2,
        "name": "role:_",
        "type_info": {
          "Custom": {
            "name": "user_role",
            "kind": {
              "Enum": [
                "admin",
                "member"
              ]
            }
          }
        }
      },
      {
        "ordinal": 3,
        "name": "token_hash",
        "type_info": "Bpchar"
      },
      {
        "ordinal": 4,
        "name": "created_at",
        "type_info": "Timestamptz"
      },
      {
        "ordinal": 5,
        "name": "expires_at",
        "type_info": "Timestamptz"
      }
    ],
    "parameters": {
      "Left": [
        "Bpchar"
      ]
    },
    "nullable": [
      false,
      false,
      false,
      false,
      false,
      false
    ]
  },
  "hash": "9489165a6047573e04adc611a46374ebce143a6c3c492ff576444561ffd89762"
}
